linkedin_v2/__init__.py
linkedin_v2/exceptions.py
linkedin_v2/linkedin.py
linkedin_v2/models.py
linkedin_v2/server.py
linkedin_v2/utils.py
python_linkedin_v2-0.9.5.dist-info/METADATA
python_linkedin_v2-0.9.5.dist-info/RECORD
python_linkedin_v2-0.9.5.dist-info/WHEEL
python_linkedin_v2-0.9.5.dist-info/top_level.txt
