Metadata-Version: 2.1
Name: python-linkedin-v2
Version: 0.9.5
Summary: Python Interface to the LinkedIn API V2
Home-page: https://github.com/HootsuiteLabs/python-linkedin-v2
Author: Rei Colina
Author-email: reinaldo13+github@gmail.com
Maintainer: Rei Colina
Maintainer-email: reinaldo13+github@gmail.com
License: MIT
Keywords: linkedin python
Platform: UNKNOWN
Classifier: Development Status :: 5 - Production/Stable
Classifier: Environment :: Console
Classifier: Intended Audience :: Developers
Classifier: License :: OSI Approved :: MIT License
Classifier: Operating System :: OS Independent
Classifier: Programming Language :: Python :: 2.7
Classifier: Programming Language :: Python :: 3
Classifier: Programming Language :: Python :: 3.4
Classifier: Natural Language :: English
Requires-Dist: requests (>=1.1.0)
Requires-Dist: requests-oauthlib (>=0.3)
